calculator/__init__.py
calculator/calculator.py
tests/__init__.py
tests/calculator_test.py
CalculatorPackageTuringRokasSertvytis-1.2.dist-info/LICENSE.md
CalculatorPackageTuringRokasSertvytis-1.2.dist-info/METADATA
CalculatorPackageTuringRokasSertvytis-1.2.dist-info/WHEEL
CalculatorPackageTuringRokasSertvytis-1.2.dist-info/top_level.txt
CalculatorPackageTuringRokasSertvytis-1.2.dist-info/RECORD
