Metadata-Version: 2.1
Name: CalculatorPackageTuringRokasSertvytis
Version: 1.2
Summary: A simple python package that allows users to perform the most basic arithmetic functions.
Author-email: rsertv <sertvytisrokas@gmail.com>
Project-URL: Homepage, https://github.com/TuringCollegeSubmissions/rsertv-DWWP.1
Classifier: Programming Language :: Python :: 3
Classifier: License :: OSI Approved :: MIT License
Classifier: Operating System :: OS Independent
Requires-Python: >=3.7
License-File: LICENSE.md
